inferiot/__init__.py
inferiot/iotclient.py
inferiot-1.0.2.dist-info/LICENSE
inferiot-1.0.2.dist-info/METADATA
inferiot-1.0.2.dist-info/WHEEL
inferiot-1.0.2.dist-info/top_level.txt
inferiot-1.0.2.dist-info/RECORD
