Metadata-Version: 2.1
Name: inferiot
Version: 1.0.2
Summary: Python facade for connecting to Smarthub's Infer IOT center
Home-page: https://github.com/prafulmaka/inferIoT
Author: Praful Maka, Mohammad Sameer Beig, Daniel Gallagher, John Groboske, Otu Ekanem
Author-email: praful.maka@gmail.com
License: MIT
Platform: UNKNOWN
Classifier: Development Status :: 2 - Pre-Alpha
Classifier: License :: OSI Approved :: MIT License
Classifier: Programming Language :: Python
Classifier: Programming Language :: Python :: 2
Classifier: Programming Language :: Python :: 2.7
Classifier: Programming Language :: Python :: 3
Classifier: Programming Language :: Python :: 3.4
Classifier: Programming Language :: Python :: 3.5
Classifier: Programming Language :: Python :: 3.6
Classifier: Programming Language :: Python :: 3.7
Requires-Dist: pandas
